easy_template/__init__.py
easy_template-0.0.2.dist-info/LICENSE
easy_template-0.0.2.dist-info/METADATA
easy_template-0.0.2.dist-info/WHEEL
easy_template-0.0.2.dist-info/top_level.txt
easy_template-0.0.2.dist-info/RECORD
