Metadata-Version: 2.1
Name: easy-template
Version: 0.0.2
Summary: Create and process templates with ease
Home-page: https://github.com/lebalz/easy_template
Author: Balthasar Hofer
Author-email: lebalz@outlook.com
License: UNKNOWN
Platform: UNKNOWN
Classifier: Programming Language :: Python :: 3
Classifier: License :: OSI Approved :: MIT License
Classifier: Operating System :: OS Independent
Requires-Python: >=3.8
